config/__init__.py
packet_capture_module/__init__.py
packet_capture_module/main.py
packet_capture_module/core/__init__.py
packet_capture_module/core/filter_engine.py
packet_capture_module/core/multicast_listener.py
packet_capture_module/core/packet.py
packet_capture_module/core/packet_buffer.py
packet_capture_module/interfaces/__init__.py
packet_capture_module/interfaces/policy_manager.py
packet_capture_module/tests/__init__.py
packet_capture_module/tests/test_filter_engine.py
packet_capture_module/tests/test_multicast_listener.py
packet_capture_module/tests/test_packet.py
packet_capture_module/tests/test_packet_buffer.py
packet_capture_module/tests/test_packet_capture_integration.py
traffic_classifier/__init__.py
traffic_classifier/bandwidth_estimator.py
traffic_classifier/classification_rule.py
traffic_classifier/dynamic_adjuster.py
traffic_classifier/integration.py
traffic_classifier/traffic_classifier.py
traffic_classifier/traffic_metadata.py
utils/__init__.py
utils/config_handler.py
utils/logging_utils.py
packet_capture_module-0.1.0.dist-info/METADATA
packet_capture_module-0.1.0.dist-info/WHEEL
packet_capture_module-0.1.0.dist-info/top_level.txt
packet_capture_module-0.1.0.dist-info/RECORD
